ht_libs/.python-version
ht_libs/README.md
ht_libs/__init__.py
ht_libs/config.py
ht_libs/do_challenge.py
ht_libs/do_hattrick_request.py
ht_libs/get_flags.py
ht_libs/get_leaguelevels.py
ht_libs/get_matchdetails.py
ht_libs/get_matches.py
ht_libs/get_series.py
ht_libs/get_teamdetails.py
ht_libs/get_trainer_avatar.py
ht_libs/get_worlddetails.py
ht_libs/pyproject.toml
ht_libs/request_token_status.py
hattrick_libs-0.19.5.dist-info/METADATA
hattrick_libs-0.19.5.dist-info/WHEEL
hattrick_libs-0.19.5.dist-info/licenses/LICENSE
hattrick_libs-0.19.5.dist-info/RECORD
