Metadata-Version: 2.4
Name: hattrick_libs
Version: 0.19.5
Summary: A library for hattrick.org data
License-File: LICENSE
Requires-Python: >=3.10
Requires-Dist: bs4>=0.0.1
Requires-Dist: lxml>=4.9.3
Requires-Dist: rauth>=0.7.3
Requires-Dist: types-beautifulsoup4>=4.12.0.7
